mbdata/__init__.py
mbdata/api/__init__.py
mbdata/api/commonsettings.py
mbdata/api/data.py
mbdata/api/errors.py
mbdata/api/includes.py
mbdata/api/serialize.py
mbdata/config.py
mbdata/data/__init__.py
mbdata/data/artist.py
mbdata/data/label.py
mbdata/data/recording.py
mbdata/data/release_group.py
mbdata/models.py
mbdata/sample_data.py
mbdata/search.py
mbdata/sql/CalculateRelatedTags.sql
mbdata/sql/CreateCollateIndexes.sql
mbdata/sql/CreateCollations.sql
mbdata/sql/CreateConstraints.sql
mbdata/sql/CreateFKConstraints.sql
mbdata/sql/CreateFunctions.sql
mbdata/sql/CreateIndexes.sql
mbdata/sql/CreateMirrorIndexes.sql
mbdata/sql/CreateMirrorOnlyFunctions.sql
mbdata/sql/CreateMirrorOnlyTriggers.sql
mbdata/sql/CreatePrimaryKeys.sql
mbdata/sql/CreateReplicationTriggers.sql
mbdata/sql/CreateReplicationTriggers2.sql
mbdata/sql/CreateSearchConfiguration.sql
mbdata/sql/CreateSearchIndexes.sql
mbdata/sql/CreateTables.sql
mbdata/sql/CreateTriggers.sql
mbdata/sql/CreateTypes.sql
mbdata/sql/CreateViews.sql
mbdata/sql/DisableLastUpdatedTriggers.sql
mbdata/sql/DropAll.sql
mbdata/sql/DropCollateIndexes.sql
mbdata/sql/DropCollations.sql
mbdata/sql/DropFKConstraints.sql
mbdata/sql/DropFunctions.sql
mbdata/sql/DropIndexes.sql
mbdata/sql/DropMirrorOnlyFunctions.sql
mbdata/sql/DropMirrorOnlyTriggers.sql
mbdata/sql/DropPrimaryKeys.sql
mbdata/sql/DropReplicationTriggers.sql
mbdata/sql/DropReplicationTriggers2.sql
mbdata/sql/DropSearchIndexes.sql
mbdata/sql/DropTables.sql
mbdata/sql/DropTriggers.sql
mbdata/sql/DropTypes.sql
mbdata/sql/DropViews.sql
mbdata/sql/EnableLastUpdatedTriggers.sql
mbdata/sql/Extensions.sql
mbdata/sql/InsertDefaultRows.sql
mbdata/sql/InsertTestData.sql
mbdata/sql/ReplicationSetup.sql
mbdata/sql/SetSequences.sql
mbdata/sql/TruncateTables.sql
mbdata/sql/caa/CreateEditFKConstraints.sql
mbdata/sql/caa/CreateFKConstraints.sql
mbdata/sql/caa/CreateFunctions.sql
mbdata/sql/caa/CreateIndexes.sql
mbdata/sql/caa/CreatePrimaryKeys.sql
mbdata/sql/caa/CreateReplicationTriggers.sql
mbdata-30.0.1.dist-info/LICENSE
mbdata-30.0.1.dist-info/METADATA
mbdata-30.0.1.dist-info/WHEEL
mbdata-30.0.1.dist-info/RECORD
