Metadata-Version: 2.3
Name: mbdata
Version: 30.0.1
Summary: MusicBrainz Database Tools
License: MIT
Author: MetaBrainz Foundation
Author-email: support@metabrainz.org
Requires-Python: >=3.7,<4.0
Classifier: License :: OSI Approved :: MIT License
Classifier: Programming Language :: Python :: 3
Classifier: Programming Language :: Python :: 3.7
Classifier: Programming Language :: Python :: 3.8
Classifier: Programming Language :: Python :: 3.9
Classifier: Programming Language :: Python :: 3.10
Classifier: Programming Language :: Python :: 3.11
Classifier: Programming Language :: Python :: 3.12
Classifier: Programming Language :: Python :: 3.13
Provides-Extra: models
Provides-Extra: search
Requires-Dist: SQLAlchemy (>=1.4.29,<2.0.0) ; extra == "models"
Requires-Dist: lxml (>=4.9.1,<5.0.0) ; extra == "search"
Requires-Dist: six (>=1.16.0,<2.0.0)
